aiarena_gym/__init__.py
aiarena_gym/environment.py
aiarena_gym/benchmarks/__init__.py
aiarena_gym/benchmarks/rules_based_agents.py
aiarena_gym/helpers/__init__.py
aiarena_gym/helpers/exporting_ops.py
aiarena_gym/helpers/game_functions.py
aiarena_gym/helpers/game_parameters.py
aiarena_gym-0.0.4.dist-info/LICENSE
aiarena_gym-0.0.4.dist-info/METADATA
aiarena_gym-0.0.4.dist-info/WHEEL
aiarena_gym-0.0.4.dist-info/top_level.txt
aiarena_gym-0.0.4.dist-info/RECORD
