Metadata-Version: 2.1
Name: aiarena-gym
Version: 0.0.4
Summary: Gym environment for training agents in the AI Arena game
Home-page: UNKNOWN
Author: ArenaX Labs Inc.
Author-email: <brandon@aiarena.io>
License: UNKNOWN
Keywords: python,gym,machine learning,reinforcement learning,fighting,game
Platform: UNKNOWN
Classifier: Programming Language :: Python :: 3
Classifier: License :: OSI Approved :: MIT License
Classifier: Operating System :: OS Independent
Requires-Dist: numpy
